render_engine_sitemap/__init__.py
render_engine_sitemap/plugin.py
render_engine_sitemap/templates/sitemap.xml
render_engine_sitemap/templates/sitemap_item.xml
render_engine_sitemap-2024.1.1a1.dist-info/LICENSE
render_engine_sitemap-2024.1.1a1.dist-info/METADATA
render_engine_sitemap-2024.1.1a1.dist-info/WHEEL
render_engine_sitemap-2024.1.1a1.dist-info/top_level.txt
render_engine_sitemap-2024.1.1a1.dist-info/RECORD
